instructify/VERSION
instructify/__init__.py
instructify/main.py
instructify/version.py
instructify-0.0.4.dist-info/LICENSE
instructify-0.0.4.dist-info/METADATA
instructify-0.0.4.dist-info/WHEEL
instructify-0.0.4.dist-info/entry_points.txt
instructify-0.0.4.dist-info/top_level.txt
instructify-0.0.4.dist-info/RECORD
