Metadata-Version: 2.1
Name: instructify
Version: 0.0.4
Summary: Instructify 📝 for easy Fine-Tuning preparation
Home-page: https://github.com/rishiraj/instructify
Author: Rishiraj Acharya
Author-email: heyrishiraj@gmail.com
Classifier: Programming Language :: Python :: 3
Classifier: License :: OSI Approved :: Apache Software License
Classifier: Operating System :: OS Independent
Requires-Python: >=3.9
License-File: LICENSE
Requires-Dist: pandas
Requires-Dist: transformers
Requires-Dist: datasets
